Metadata-Version: 2.1
Name: ddls3utils
Version: 0.0.7
Summary: S3 utils
Home-page: UNKNOWN
Author: Shen Wang
Author-email: nedlitex0053@gmail.com
License: UNKNOWN
Platform: UNKNOWN
Classifier: Programming Language :: Python :: 3
Classifier: License :: OSI Approved :: MIT License
Classifier: Operating System :: OS Independent
